CODE_OF_CONDUCT.rst
CONTRIBUTING.rst
LICENSE.txt
MANIFEST.in
README.rst
setup.py
ratelimit/__init__.py
ratelimit/decorators.py
ratelimit/exception.py
ratelimit/utils.py
tiriel_ratelimit.egg-info/PKG-INFO
tiriel_ratelimit.egg-info/SOURCES.txt
tiriel_ratelimit.egg-info/dependency_links.txt
tiriel_ratelimit.egg-info/not-zip-safe
tiriel_ratelimit.egg-info/top_level.txt