Metadata-Version: 1.1
Name: tiriel-ratelimit
Version: 2.2.1
Summary: API rate limit decorator
Home-page: https://github.com/Jorge-Rodriguez/ratelimit
Author: Jorge Rodriguez
Author-email: jorge.rodriguez@tiriel.eu
License: MIT
Keywords: ratelimit,api,decorator
Platform: UNKNOWN
Classifier: Development Status :: 5 - Production/Stable
Classifier: Intended Audience :: Developers
Classifier: License :: OSI Approved :: MIT License
Classifier: Natural Language :: English
Classifier: Programming Language :: Python
Classifier: Topic :: Software Development
